rtl/__init__.py
rtl/_pprint_py2.py
rtl/_pprint_py3.py
rtl/compat.py
rtl/helpers.py
rtl/pretty_printer.py
rtl/reshaper.py
rtl/tests/__init__.py
rtl/tests/test_pprint.py
rtl/tests/test_reshaper.py
rtl-0.4.3.dist-info/DESCRIPTION.rst
rtl-0.4.3.dist-info/METADATA
rtl-0.4.3.dist-info/RECORD
rtl-0.4.3.dist-info/WHEEL
rtl-0.4.3.dist-info/entry_points.txt
rtl-0.4.3.dist-info/metadata.json
rtl-0.4.3.dist-info/top_level.txt
